pyRVtest/__init__.py
pyRVtest/construction.py
pyRVtest/options.py
pyRVtest/primitives.py
pyRVtest/version.py
pyRVtest/configurations/__init__.py
pyRVtest/configurations/formulation.py
pyRVtest/data/__init__.py
pyRVtest/data/f_critical_values_power_rho.csv
pyRVtest/data/f_critical_values_size_rho.csv
pyRVtest/data/__pycache__/__init__.cpython-39.pyc~Stashed changes
pyRVtest/economies/__init__.py
pyRVtest/economies/economy.py
pyRVtest/economies/problem.py
pyRVtest/results/__init__.py
pyRVtest/results/problem_results.py
pyRVtest/results/results.py
pyRVtest/utilities/__init__.py
pyRVtest/utilities/basics.py
pyrvtest-0.3.2.dist-info/licenses/LICENSE.txt
pyrvtest-0.3.2.dist-info/METADATA
pyrvtest-0.3.2.dist-info/WHEEL
pyrvtest-0.3.2.dist-info/top_level.txt
pyrvtest-0.3.2.dist-info/RECORD
