Metadata-Version: 2.4
Name: pyRVtest
Version: 0.3.2
Summary: Code to perform econometric test of firm conduct
Home-page: https://github.com/anyatarascina/pyRVtest
Author: Marco Duarte, Lorenzo Magnolfi, Mikkel Solvsten, Christopher Sullivan, Anya Tarascina
Author-email: chris.sullivan.econ@gmail.com
License: MIT
Requires-Python: >=3.7
License-File: LICENSE.txt
Requires-Dist: numpy>=1.17.0
Requires-Dist: patsy>=0.5.1
Requires-Dist: scipy>=1.2.0
Requires-Dist: sympy>=1.1.0
Requires-Dist: statsmodels>=0.12.2
Requires-Dist: pyblp>=1.0.0
Provides-Extra: docs
Requires-Dist: sphinx==5.0.2; extra == "docs"
Requires-Dist: pandas; extra == "docs"
Requires-Dist: ipython; extra == "docs"
Requires-Dist: astunparse; extra == "docs"
Requires-Dist: sphinx-rtd-theme==1.1.1; extra == "docs"
Requires-Dist: nbsphinx==0.8.11; extra == "docs"
Requires-Dist: jinja2==3.0.3; extra == "docs"
Requires-Dist: docutils==0.17.1; extra == "docs"
Requires-Dist: numpydoc; extra == "docs"
Dynamic: author
Dynamic: author-email
Dynamic: description
Dynamic: home-page
Dynamic: license
Dynamic: license-file
Dynamic: provides-extra
Dynamic: requires-dist
Dynamic: requires-python
Dynamic: summary
